explain_me/__init__.py
explain_me/class_inspect.py
explain_me/visual.py
explain_me-0.2.0.dist-info/WHEEL
explain_me-0.2.0.dist-info/METADATA
explain_me-0.2.0.dist-info/RECORD
