Metadata-Version: 2.1
Name: explain-me
Version: 0.2.0
Summary: package explain data concept python
Author: vaziria
Author-email: manorder123@gmail.com
Requires-Python: >=3.9,<4.0
Classifier: Programming Language :: Python :: 3
Classifier: Programming Language :: Python :: 3.10
Classifier: Programming Language :: Python :: 3.9
Requires-Dist: pydantic (>=1.10.2,<2.0.0)
